LICENSE.txt
MANIFEST.in
README.md
setup.cfg
setup.py
topsis/102003718_code.py
topsis/__init__.py
topsis_102003718.egg-info/PKG-INFO
topsis_102003718.egg-info/SOURCES (2).txt
topsis_102003718.egg-info/SOURCES.txt
topsis_102003718.egg-info/dependency_links.txt
topsis_102003718.egg-info/top_level.txt