Metadata-Version: 2.1
Name: topsis-102003718
Version: 1.0.1
Summary: topsis implementation
Author: Jasmeet Kaur Gill
Author-email: jasmeetshergill101@gmail.com
Classifier: Programming Language :: Python :: 3
Classifier: License :: OSI Approved :: MIT License
Classifier: Operating System :: OS Independent
Requires-Python: >=3.6
License-File: LICENSE.txt
